{
	"frame": {
		"name": "frame1",
		"position": [100,50],
		"size": [500,500],
		"background_color": [0,0,100],
		"contents": {
			"frame": {
				"name": "frame2",
				"position": [200,100],
				"size": [300,300],
				"background_color": [0,50,100],
				"contents": {
					"button": {
						"name": "harry the button",
						"position": [250,120],
						"size": [200,200],
						"background_color": [100,0,0],
						"contents": {
							"label": {
								"name": "richard",
								"position": [260,150],
								"font_size": 30,
								"auto_size": true
							}
						}
					}
				}
			}
		}
	}
}